p115/.DS_Store
p115/__init__.py
python_115-0.1.0.dist-info/METADATA
python_115-0.1.0.dist-info/WHEEL
python_115-0.1.0.dist-info/RECORD
