Metadata-Version: 2.1
Name: python-115
Version: 0.1.0
Summary: Python 115 webdisk client.
Home-page: https://github.com/ChenyangGao/p115client
License: MIT
Keywords: 115,webdisk,client
Author: ChenyangGao
Author-email: wosiwujm@gmail.com
Requires-Python: >=3.12,<4.0
Classifier: Development Status :: 4 - Beta
Classifier: Intended Audience :: Developers
Classifier: License :: OSI Approved :: MIT License
Classifier: Operating System :: OS Independent
Classifier: Programming Language :: Python
Classifier: Programming Language :: Python :: 3
Classifier: Programming Language :: Python :: 3.12
Classifier: Programming Language :: Python :: 3.13
Classifier: Programming Language :: Python :: 3 :: Only
Classifier: Topic :: Software Development
Classifier: Topic :: Software Development :: Libraries
Classifier: Topic :: Software Development :: Libraries :: Python Modules
Requires-Dist: p115client
Project-URL: Documentation, https://p115client.readthedocs.io
Project-URL: Repository, https://github.com/ChenyangGao/p115client
